nbsp_python/__init__.py
nbsp_python/_core.cp312-win_amd64.pyd
nbsp_python-1.1.dist-info/METADATA
nbsp_python-1.1.dist-info/WHEEL
nbsp_python-1.1.dist-info/entry_points.txt
nbsp_python-1.1.dist-info/licenses/LICENSE
nbsp_python-1.1.dist-info/RECORD
