Metadata-Version: 2.1
Name: nbsp_python
Version: 1.1
Summary: Python bindings for NBioBSP using C++ and pybind11
Author-Email: Lucas Andreatta <drea.pierra@gmail.com>
Classifier: Development Status :: 4 - Beta
Classifier: Programming Language :: Python :: 3 :: Only
Classifier: Programming Language :: Python :: 3.10
Classifier: Programming Language :: Python :: 3.11
Requires-Python: >=3.10
Provides-Extra: test
Requires-Dist: pytest; extra == "test"
License-File: LICENSE
